ecrivain/__init__.py
ecrivain/xlsx.py
ecrivain-0.1.2.dist-info/WHEEL
ecrivain-0.1.2.dist-info/METADATA
ecrivain-0.1.2.dist-info/RECORD
